fastlmm/__init__.py
fastlmm/association/FastLmmSet.py
fastlmm/association/FastLmmSetLOOC.py
fastlmm/association/LeaveOneChromosomeOut.py
fastlmm/association/LocoGwas.py
fastlmm/association/PairResult.py
fastlmm/association/PrecomputeLocoPcs.py
fastlmm/association/Result.py
fastlmm/association/__init__.py
fastlmm/association/_matchscript.py
fastlmm/association/_pipelines.py
fastlmm/association/epistasis.py
fastlmm/association/fixed.py
fastlmm/association/gwas.py
fastlmm/association/gwas_eval.py
fastlmm/association/heritability_spatial_correction.py
fastlmm/association/lrt.py
fastlmm/association/meta_analysis.py
fastlmm/association/score.py
fastlmm/association/single_snp.py
fastlmm/association/single_snp_all_plus_select.py
fastlmm/association/single_snp_linreg.py
fastlmm/association/single_snp_scale.py
fastlmm/association/single_snp_select.py
fastlmm/association/snp_set.py
fastlmm/association/testCV.py
fastlmm/association/varcomp_test.py
fastlmm/association/windowing_gwas.py
fastlmm/association/Fastlmm_autoselect/FastLmmC.Manual.pdf
fastlmm/association/Fastlmm_autoselect/FastLmmC.exe
fastlmm/association/Fastlmm_autoselect/fastlmmc
fastlmm/association/Fastlmm_autoselect/libiomp5md.dll
fastlmm/association/altset_list/__init__.py
fastlmm/association/altset_list/consecutive.py
fastlmm/association/altset_list/minmaxsetsize.py
fastlmm/association/altset_list/snpandsetnamecollection.py
fastlmm/association/altset_list/subset.py
fastlmm/association/tests/Cv.py
fastlmm/association/tests/LRT_up.py
fastlmm/association/tests/Lrt.py
fastlmm/association/tests/Sc.py
fastlmm/association/tests/__init__.py
fastlmm/association/tests/test_gpu_perf.py
fastlmm/association/tests/test_gwas.py
fastlmm/association/tests/test_heritability_spatial_correction.py
fastlmm/association/tests/test_single_snp.py
fastlmm/association/tests/test_single_snp_all_plus_select.py
fastlmm/association/tests/test_single_snp_linreg.py
fastlmm/association/tests/test_single_snp_scale.py
fastlmm-0.5.10.dist-info/AUTHORS.txt
fastlmm-0.5.10.dist-info/LICENSE.md
fastlmm-0.5.10.dist-info/METADATA
fastlmm-0.5.10.dist-info/WHEEL
fastlmm-0.5.10.dist-info/top_level.txt
fastlmm-0.5.10.dist-info/RECORD
