Metadata-Version: 2.1
Name: fastlmm
Version: 0.5.10
Summary: Fast GWAS
Home-page: https://fastlmm.github.io/
Author: FaST-LMM Team
Author-email: fastlmm-dev@python.org
License: Apache 2.0
Project-URL: Bug Tracker, https://github.com/fastlmm/FaST-LMM/issues
Project-URL: Documentation, http://fastlmm.github.io/FaST-LMM
Project-URL: Source Code, https://github.com/fastlmm/FaST-LMM
Keywords: gwas bioinformatics LMMs MLMs linear mixed models genomics genetics python
Platform: UNKNOWN
Classifier: Programming Language :: Python :: 3.7
Classifier: Programming Language :: Python :: 3.8
Classifier: Programming Language :: Python :: 3.9
Classifier: Programming Language :: Python :: 3
Classifier: Programming Language :: Python
